chunkops-0.3.0.dist-info/licenses/LICENSE
chunkops_cli/__init__.py
chunkops_cli/auth.py
chunkops_cli/cli.py
chunkops_cli/cloud.py
chunkops_cli/config.py
chunkops_cli/deduper.py
chunkops_cli/extractor.py
chunkops_cli/hierarchical_chunker.py
chunkops-0.3.0.dist-info/METADATA
chunkops-0.3.0.dist-info/WHEEL
chunkops-0.3.0.dist-info/entry_points.txt
chunkops-0.3.0.dist-info/top_level.txt
chunkops-0.3.0.dist-info/RECORD
