Metadata-Version: 2.4
Name: chunkops
Version: 0.3.0
Summary: The CI/CD Pipeline for RAG - Detect semantic conflicts before they become hallucinations
Home-page: https://chunkops.ai
Author: ChunkOps
Author-email: ChunkOps <hello@chunkops.ai>
License-Expression: MIT
Project-URL: Homepage, https://chunkops.ai
Project-URL: Documentation, https://chunkops.ai/docs
Project-URL: Repository, https://github.com/chunkops/chunkops-cli
Keywords: rag,pdf,duplicate-detection,semantic-conflicts,llm,rag-pipeline,document-analysis
Classifier: Development Status :: 3 - Alpha
Classifier: Intended Audience :: Developers
Classifier: Programming Language :: Python :: 3
Classifier: Programming Language :: Python :: 3.8
Classifier: Programming Language :: Python :: 3.9
Classifier: Programming Language :: Python :: 3.10
Classifier: Programming Language :: Python :: 3.11
Classifier: Programming Language :: Python :: 3.12
Requires-Python: >=3.8
License-File: LICENSE
Requires-Dist: PyMuPDF>=1.23.0
Requires-Dist: sentence-transformers>=2.2.0
Requires-Dist: tiktoken>=0.5.0
Requires-Dist: langchain-text-splitters>=0.2.0
Requires-Dist: rich>=13.0.0
Requires-Dist: typer>=0.9.0
Requires-Dist: pyyaml>=6.0
Requires-Dist: requests>=2.31.0
Requires-Dist: numpy>=1.21.0
Provides-Extra: dev
Requires-Dist: pytest>=7.0.0; extra == "dev"
Requires-Dist: black>=23.0.0; extra == "dev"
Dynamic: author
Dynamic: home-page
Dynamic: license-file
Dynamic: requires-python
